naotw/__init__.py
naotw/gis.py
naotw/gpt.py
naotw/交通事故分析.py
naotw-1.35.dist-info/METADATA
naotw-1.35.dist-info/WHEEL
naotw-1.35.dist-info/licenses/LICENSE
naotw-1.35.dist-info/RECORD
