Metadata-Version: 2.3
Name: naotw
Version: 1.35
Summary: 中華民國審計部套件
Project-URL: Homepage, https://github.com/fhopecc/naotw
Project-URL: Bug Tracker, https://github.com/fhopecc/naotw/issues
Author-email: fhopecc <fhopecc@gmail.com>
License:                     GNU GENERAL PUBLIC LICENSE
License-File: LICENSE
Classifier: License :: OSI Approved :: MIT License
Classifier: Operating System :: OS Independent
Classifier: Programming Language :: Python :: 3
Requires-Python: >=3.7
Requires-Dist: geopandas
Requires-Dist: simplekml
Requires-Dist: zhongwen
